wuncolors/__init__.py
wuncolors/color.py
wuncolors/formats.py
wuncolors/utils.py
wuncolors-0.1.2.dist-info/LICENSE.txt
wuncolors-0.1.2.dist-info/METADATA
wuncolors-0.1.2.dist-info/WHEEL
wuncolors-0.1.2.dist-info/RECORD
